Metadata-Version: 1.0
Name: whoi
Version: 0.3
Summary: for testing
Home-page: UNKNOWN
Author: idk
Author-email: idk@emaill.com
License: UNKNOWN
Platform: UNKNOWN
